earthshadow.py
earthshadow-1.0.5.dist-info/LICENSE
earthshadow-1.0.5.dist-info/METADATA
earthshadow-1.0.5.dist-info/WHEEL
earthshadow-1.0.5.dist-info/top_level.txt
earthshadow-1.0.5.dist-info/RECORD
