Metadata-Version: 2.1
Name: earthshadow
Version: 1.0.5
Summary: An astropy-based package to find the coordinates of the Earth's shadow.
Author-email: Guy Nir <guynir42@gmail.com>
Project-URL: Homepage, https://github.com/guynir42/earthshadow
Project-URL: Bug Tracker, https://github.com/guynir42/earthshadow/issues
Classifier: Programming Language :: Python :: 3
Classifier: License :: OSI Approved :: MIT License
Classifier: Operating System :: OS Independent
Requires-Python: >=3.8
License-File: LICENSE
Requires-Dist: numpy
Requires-Dist: astropy
Requires-Dist: matplotlib
